spds/__init__.py
spds-0.0.0a0.dist-info/LICENSE
spds-0.0.0a0.dist-info/METADATA
spds-0.0.0a0.dist-info/WHEEL
spds-0.0.0a0.dist-info/top_level.txt
spds-0.0.0a0.dist-info/RECORD
