Metadata-Version: 2.1
Name: spds
Version: 0.0.0a0
Summary: Open sourse software for pipeline design
Home-page: UNKNOWN
Author: Abhishek Mamgain
License: UNKNOWN
Platform: UNKNOWN
Classifier: Programming Language :: Python :: 3
Classifier: License :: OSI Approved :: MIT License
Classifier: Operating System :: OS Independent
Requires-Python: >=3.6
License-File: LICENSE
